<?xml version="1.0" encoding="UTF-8"?>
<objects serializationModel="Studio.02.02.00">
	<object class="ParameterPreset" id="{6eb0ef9b-b008-4afe-a647-2b62d36a8ee6}">
		<property name="name">
			<value>bird_1_note</value>
		</property>
		<relationship name="folder">
			<destination>{a1ea3efd-4638-41ea-96ce-420916473357}</destination>
		</relationship>
		<relationship name="parameter">
			<destination>{3d6e3fda-34fd-43ec-8703-11386547badb}</destination>
		</relationship>
	</object>
	<object class="GameParameter" id="{3d6e3fda-34fd-43ec-8703-11386547badb}">
		<property name="parameterType">
			<value>2</value>
		</property>
		<property name="maximum">
			<value>13</value>
		</property>
		<property name="enumerationLabels">
			<value>C</value>
			<value>Csharp</value>
			<value>D</value>
			<value>Dsharp</value>
			<value>E</value>
			<value>F</value>
			<value>Fsharp</value>
			<value>G</value>
			<value>Gsharp</value>
			<value>A</value>
			<value>Asharp</value>
			<value>B</value>
			<value>Off</value>
		</property>
		<property name="initialValue">
			<value>12</value>
		</property>
	</object>
</objects>
